setup.py
bin/rant
rant/__init__.py
rant/generator.py
rant/installer.py
rant/publisher.py
rant.egg-info/PKG-INFO
rant.egg-info/SOURCES.txt
rant.egg-info/dependency_links.txt
rant.egg-info/requires.txt
rant.egg-info/top_level.txt