Metadata-Version: 1.0
Name: rant
Version: 0.2.2
Summary: A CLI driven blog-aware website generator. It is intended to make maintianing a blog or personal website easy using only your favorite console editor such as Vim, and a few simple commands
Home-page: http://github.com/lrvick/rant
Author: Lance R. Vick
Author-email: lance@lrvick.net
License: LICENSE.md
Platform: UNKNOWN
